ctype/__init__.py
ctype/_cbuiltin/__init__.py
ctype/_cerr/__init__.py
ctype/_ctypes/__init__.py
ctype/_ctypes/boolean.py
ctype/_ctypes/char.py
ctype/_ctypes/ctype.py
ctype/_ctypes/double.py
ctype/_ctypes/floats.py
ctype/_ctypes/ints.py
ctype/_ctypes/long.py
ctype/_ctypes/longlong.py
ctype/_ctypes/ptr.py
ctype/_ctypes/short.py
ctype/_ctypes/structs.py
ctype/_ctypes/typedef.py
ctype/_ctypes/uint.py
ctype/_ctypes/ulong.py
ctype/_ctypes/ulonglong.py
ctype/_ctypes/ushort.py
ctype/_ctypes/void.py
ctype/tests/__init__.py
ctype-7.4.1.dist-info/METADATA
ctype-7.4.1.dist-info/WHEEL
ctype-7.4.1.dist-info/top_level.txt
ctype-7.4.1.dist-info/RECORD
