Metadata-Version: 2.1
Name: ctype
Version: 7.4.1
Summary: Interact with cython, python, ctypes, and use other c/c++ tools
Home-page: https://github.com/notepads/ctype
Author: notepads
Author-email: notepads.py@gmail.com
License: MIT
Keywords: ctype,ctypes,cython,cpython,cpy,python,c,c++
Classifier: License :: OSI Approved :: MIT License
Classifier: Development Status :: 5 - Production/Stable
Classifier: Development Status :: 4 - Beta
Classifier: Development Status :: 3 - Alpha
Classifier: Development Status :: 2 - Pre-Alpha
Classifier: Development Status :: 1 - Planning
Classifier: Intended Audience :: Developers
Classifier: Intended Audience :: Science/Research
Classifier: License :: OSI Approved :: MIT License
Classifier: Programming Language :: Python
Classifier: Topic :: Software Development :: Libraries
Classifier: Topic :: Software Development :: Libraries :: Python Modules
Classifier: Topic :: Scientific/Engineering
Classifier: Topic :: Scientific/Engineering :: Mathematics
Classifier: Typing :: Typed
Requires-Python: >=3.7
